{
  "meta": {
    "generated": "2026-02-12T14:05:22",
    "palette_count": 9,
    "domain_count": 26,
    "agent_count": 28,
    "palettes": ["cyberpunk", "viridis", "magma", "inferno", "plasma", "cividis", "mako", "rocket", "turbo"],
    "domains": ["alchemy", "bushcraft", "compliance", "containerization", "data-serialization", "defensive", "design", "devops", "esoteric", "gardening", "general", "git", "intellectual-property", "jigsawr", "mcp-integration", "mlops", "morphic", "observability", "project-management", "r-packages", "reporting", "review", "swarm", "tcg", "web-dev", "workflow-visualization"],
    "agents": ["alchemist", "auditor", "code-reviewer", "designer", "devops-engineer", "gardener", "gxp-validator", "ip-analyst", "jigsawr-developer", "martial-artist", "mlops-engineer", "mystic", "polymath", "project-manager", "putior-integrator", "quarto-developer", "r-developer", "security-analyst", "senior-data-scientist", "senior-researcher", "senior-software-developer", "senior-ux-ui-specialist", "senior-web-designer", "shapeshifter", "survivalist", "swarm-strategist", "tcg-specialist", "web-developer"]
  },
  "palettes": {
    "cyberpunk": {
      "domains": {
        "alchemy": "#ffaa33",
        "bushcraft": "#88cc44",
        "compliance": "#ff3366",
        "containerization": "#44ddff",
        "data-serialization": "#44aaff",
        "defensive": "#ff4444",
        "design": "#ff88dd",
        "devops": "#00ff88",
        "esoteric": "#dd44ff",
        "gardening": "#44bb66",
        "general": "#ccccff",
        "git": "#66ffcc",
        "intellectual-property": "#33ccff",
        "jigsawr": "#22ddaa",
        "mcp-integration": "#00ccaa",
        "mlops": "#aa66ff",
        "morphic": "#bb88ff",
        "observability": "#ffaa00",
        "project-management": "#ff8844",
        "r-packages": "#00f0ff",
        "reporting": "#ffdd00",
        "review": "#ff66aa",
        "swarm": "#aadd44",
        "tcg": "#ff5577",
        "web-dev": "#ff6633",
        "workflow-visualization": "#66dd88"
      },
      "agents": {
        "alchemist": "#ffaa33",
        "auditor": "#ff7744",
        "code-reviewer": "#ff66aa",
        "designer": "#ff88dd",
        "devops-engineer": "#00ff88",
        "gardener": "#44bb66",
        "gxp-validator": "#ff3399",
        "ip-analyst": "#33ccff",
        "jigsawr-developer": "#22ddaa",
        "martial-artist": "#ff4466",
        "mlops-engineer": "#bb77ff",
        "mystic": "#dd44ff",
        "polymath": "#eedd44",
        "project-manager": "#ff8844",
        "putior-integrator": "#66dd88",
        "quarto-developer": "#33ddcc",
        "r-developer": "#00f0ff",
        "security-analyst": "#ff3333",
        "senior-data-scientist": "#aa66ff",
        "senior-researcher": "#ffaa00",
        "senior-software-developer": "#44ddff",
        "senior-ux-ui-specialist": "#66ffcc",
        "senior-web-designer": "#ffdd00",
        "shapeshifter": "#bb88ff",
        "survivalist": "#88cc44",
        "swarm-strategist": "#aadd44",
        "tcg-specialist": "#ff5577",
        "web-developer": "#ff6633"
      }
    },
    "viridis": {
      "domains": {
        "alchemy": "#440154",
        "bushcraft": "#471063",
        "compliance": "#481E6F",
        "containerization": "#472B7A",
        "data-serialization": "#453882",
        "defensive": "#414487",
        "design": "#3C4F8A",
        "devops": "#375A8C",
        "esoteric": "#32658E",
        "gardening": "#2E6F8E",
        "general": "#2A788E",
        "git": "#26828E",
        "intellectual-property": "#228B8D",
        "jigsawr": "#1F958B",
        "mcp-integration": "#1F9F88",
        "mlops": "#22A884",
        "morphic": "#2CB17E",
        "observability": "#3ABA76",
        "project-management": "#4DC36B",
        "r-packages": "#62CB5F",
        "reporting": "#7AD151",
        "review": "#93D741",
        "swarm": "#AEDC30",
        "tcg": "#C9E120",
        "web-dev": "#E5E419",
        "workflow-visualization": "#FDE725"
      },
      "agents": {
        "alchemist": "#482576",
        "auditor": "#472E7C",
        "code-reviewer": "#453881",
        "designer": "#424086",
        "devops-engineer": "#3E4989",
        "gardener": "#3B518B",
        "gxp-validator": "#375A8C",
        "ip-analyst": "#34618D",
        "jigsawr-developer": "#30698E",
        "martial-artist": "#2D718E",
        "mlops-engineer": "#2A778E",
        "mystic": "#277F8E",
        "polymath": "#25858E",
        "project-manager": "#228D8D",
        "putior-integrator": "#20938C",
        "quarto-developer": "#1E9B8A",
        "r-developer": "#1FA187",
        "security-analyst": "#23A983",
        "senior-data-scientist": "#29AF7F",
        "senior-researcher": "#34B679",
        "senior-software-developer": "#40BD72",
        "senior-ux-ui-specialist": "#4EC36B",
        "senior-web-designer": "#5DC962",
        "shapeshifter": "#6ECE58",
        "survivalist": "#81D34D",
        "swarm-strategist": "#94D741",
        "tcg-specialist": "#A8DB34",
        "web-developer": "#BBDF27"
      }
    },
    "magma": {
      "domains": {
        "alchemy": "#000004",
        "bushcraft": "#050416",
        "compliance": "#0F0B2C",
        "containerization": "#1B1043",
        "data-serialization": "#2A115C",
        "defensive": "#3B0F70",
        "design": "#4C117A",
        "devops": "#5C167F",
        "esoteric": "#6C1D81",
        "gardening": "#7C2382",
        "general": "#8C2981",
        "git": "#9C2E7F",
        "intellectual-property": "#AD347C",
        "jigsawr": "#BE3A77",
        "mcp-integration": "#CF4070",
        "mlops": "#DE4968",
        "morphic": "#EA5661",
        "observability": "#F4665C",
        "project-management": "#F9795D",
        "r-packages": "#FC8C63",
        "reporting": "#FE9F6D",
        "review": "#FEB27A",
        "swarm": "#FEC589",
        "tcg": "#FED89A",
        "web-dev": "#FDEBAC",
        "workflow-visualization": "#FCFDBF"
      },
      "agents": {
        "alchemist": "#150E37",
        "auditor": "#1E1149",
        "code-reviewer": "#2A115B",
        "designer": "#36106B",
        "devops-engineer": "#440F76",
        "gardener": "#50127B",
        "gxp-validator": "#5C167F",
        "ip-analyst": "#671C80",
        "jigsawr-developer": "#732081",
        "martial-artist": "#7F2582",
        "mlops-engineer": "#8B2981",
        "mystic": "#972D80",
        "polymath": "#A3307E",
        "project-manager": "#AF357B",
        "putior-integrator": "#BC3978",
        "quarto-developer": "#C83E73",
        "r-developer": "#D4436E",
        "security-analyst": "#DF4A68",
        "senior-data-scientist": "#E85362",
        "senior-researcher": "#F05F5E",
        "senior-software-developer": "#F66C5C",
        "senior-ux-ui-specialist": "#F9795D",
        "senior-web-designer": "#FC8961",
        "shapeshifter": "#FD9768",
        "survivalist": "#FEA571",
        "swarm-strategist": "#FEB37B",
        "tcg-specialist": "#FEC185",
        "web-developer": "#FECE91"
      }
    },
    "inferno": {
      "domains": {
        "alchemy": "#000004",
        "bushcraft": "#050417",
        "compliance": "#11092E",
        "containerization": "#1F0C47",
        "data-serialization": "#310A5C",
        "defensive": "#420A68",
        "design": "#520E6D",
        "devops": "#63156E",
        "esoteric": "#731A6E",
        "gardening": "#84206B",
        "general": "#932667",
        "git": "#A32C61",
        "intellectual-property": "#B3325A",
        "jigsawr": "#C23B4F",
        "mcp-integration": "#D04545",
        "mlops": "#DD513A",
        "morphic": "#E75E2E",
        "observability": "#EF6E20",
        "project-management": "#F67F13",
        "r-packages": "#FA9207",
        "reporting": "#FCA50A",
        "review": "#FBB81D",
        "swarm": "#F9CC36",
        "tcg": "#F4E055",
        "web-dev": "#F2F27C",
        "workflow-visualization": "#FCFFA4"
      },
      "agents": {
        "alchemist": "#170C3A",
        "auditor": "#230C4C",
        "code-reviewer": "#300A5C",
        "designer": "#3D0965",
        "devops-engineer": "#4A0C6B",
        "gardener": "#550F6D",
        "gxp-validator": "#62146E",
        "ip-analyst": "#6E186E",
        "jigsawr-developer": "#7A1D6D",
        "martial-artist": "#86216B",
        "mlops-engineer": "#922568",
        "mystic": "#9E2A63",
        "polymath": "#A92E5E",
        "project-manager": "#B53458",
        "putior-integrator": "#C03A51",
        "quarto-developer": "#CB4149",
        "r-developer": "#D44942",
        "security-analyst": "#DE5238",
        "senior-data-scientist": "#E65D30",
        "senior-researcher": "#EC6726",
        "senior-software-developer": "#F2741C",
        "senior-ux-ui-specialist": "#F68013",
        "senior-web-designer": "#F98D09",
        "shapeshifter": "#FB9C06",
        "survivalist": "#FCAA0F",
        "swarm-strategist": "#FBB91E",
        "tcg-specialist": "#F9C72F",
        "web-developer": "#F6D645"
      }
    },
    "plasma": {
      "domains": {
        "alchemy": "#0D0887",
        "bushcraft": "#260591",
        "compliance": "#39049A",
        "containerization": "#4A03A1",
        "data-serialization": "#5B01A5",
        "defensive": "#6A00A8",
        "design": "#7A02A8",
        "devops": "#8908A6",
        "esoteric": "#9714A1",
        "gardening": "#A51F99",
        "general": "#B12A90",
        "git": "#BC3587",
        "intellectual-property": "#C6417D",
        "jigsawr": "#D04D73",
        "mcp-integration": "#D9586A",
        "mlops": "#E16462",
        "morphic": "#E87059",
        "observability": "#EF7D51",
        "project-management": "#F58A47",
        "r-packages": "#F9983E",
        "reporting": "#FCA636",
        "review": "#FDB52E",
        "swarm": "#FDC527",
        "tcg": "#FBD624",
        "web-dev": "#F6E826",
        "workflow-visualization": "#F0F921"
      },
      "agents": {
        "alchemist": "#42049E",
        "auditor": "#4E02A2",
        "code-reviewer": "#5A01A5",
        "designer": "#6600A7",
        "devops-engineer": "#7201A8",
        "gardener": "#7D03A8",
        "gxp-validator": "#8808A6",
        "ip-analyst": "#930FA3",
        "jigsawr-developer": "#9D189D",
        "martial-artist": "#A62098",
        "mlops-engineer": "#B02991",
        "mystic": "#B83289",
        "polymath": "#C03A83",
        "project-manager": "#C8437B",
        "putior-integrator": "#CE4B75",
        "quarto-developer": "#D5546E",
        "r-developer": "#DB5C68",
        "security-analyst": "#E26561",
        "senior-data-scientist": "#E76F5B",
        "senior-researcher": "#EC7754",
        "senior-software-developer": "#F1814D",
        "senior-ux-ui-specialist": "#F58B47",
        "senior-web-designer": "#F89540",
        "shapeshifter": "#FB9F3A",
        "survivalist": "#FDAB33",
        "swarm-strategist": "#FDB62E",
        "tcg-specialist": "#FDC229",
        "web-developer": "#FCCE25"
      }
    },
    "cividis": {
      "domains": {
        "alchemy": "#00204D",
        "bushcraft": "#00275E",
        "compliance": "#002E6F",
        "containerization": "#00366E",
        "data-serialization": "#213D6D",
        "defensive": "#31446B",
        "design": "#3E4B6B",
        "devops": "#49526B",
        "esoteric": "#545A6C",
        "gardening": "#5D616E",
        "general": "#666970",
        "git": "#6F7073",
        "intellectual-property": "#787777",
        "jigsawr": "#828079",
        "mcp-integration": "#8B8779",
        "mlops": "#958F78",
        "morphic": "#9F9777",
        "observability": "#AA9F75",
        "project-management": "#B5A971",
        "r-packages": "#C0B16E",
        "reporting": "#CBBA69",
        "review": "#D6C364",
        "swarm": "#E1CC5D",
        "tcg": "#ECD654",
        "web-dev": "#F9E04A",
        "workflow-visualization": "#FFEA46"
      },
      "agents": {
        "alchemist": "#00326F",
        "auditor": "#0B376E",
        "code-reviewer": "#203D6D",
        "designer": "#2D426C",
        "devops-engineer": "#37486B",
        "gardener": "#404D6B",
        "gxp-validator": "#49526B",
        "ip-analyst": "#50576C",
        "jigsawr-developer": "#585D6D",
        "martial-artist": "#5F636E",
        "mlops-engineer": "#656870",
        "mystic": "#6C6E72",
        "polymath": "#727374",
        "project-manager": "#797977",
        "putior-integrator": "#807E79",
        "quarto-developer": "#878479",
        "r-developer": "#8E8A79",
        "security-analyst": "#969078",
        "senior-data-scientist": "#9E9677",
        "senior-researcher": "#A59C76",
        "senior-software-developer": "#AEA374",
        "senior-ux-ui-specialist": "#B5A971",
        "senior-web-designer": "#BDAF6F",
        "shapeshifter": "#C5B56C",
        "survivalist": "#CEBC68",
        "swarm-strategist": "#D6C364",
        "tcg-specialist": "#DECA5F",
        "web-developer": "#E7D159"
      }
    },
    "mako": {
      "domains": {
        "alchemy": "#03051A",
        "bushcraft": "#100B23",
        "compliance": "#1F122D",
        "containerization": "#2E1739",
        "data-serialization": "#3D1A42",
        "defensive": "#4C1D4B",
        "design": "#5C1E51",
        "devops": "#6D1F56",
        "esoteric": "#7E1E5A",
        "gardening": "#901D5B",
        "general": "#A11A5B",
        "git": "#B21758",
        "intellectual-property": "#C31753",
        "jigsawr": "#D2204C",
        "mcp-integration": "#DE2E44",
        "mlops": "#E83F3F",
        "morphic": "#EE523F",
        "observability": "#F16646",
        "project-management": "#F47953",
        "r-packages": "#F58B63",
        "reporting": "#F69C73",
        "review": "#F6AD85",
        "swarm": "#F6BD9A",
        "tcg": "#F7CDB0",
        "web-dev": "#F8DCC7",
        "workflow-visualization": "#FAEBDD"
      },
      "agents": {
        "alchemist": "#261433",
        "auditor": "#31183B",
        "code-reviewer": "#3D1A42",
        "designer": "#481C48",
        "devops-engineer": "#541E4E",
        "gardener": "#601F52",
        "gxp-validator": "#6D1F56",
        "ip-analyst": "#791F59",
        "jigsawr-developer": "#861E5B",
        "martial-artist": "#931C5B",
        "mlops-engineer": "#9F1A5B",
        "mystic": "#AC1759",
        "polymath": "#B91657",
        "project-manager": "#C51852",
        "putior-integrator": "#D01E4D",
        "quarto-developer": "#D92847",
        "r-developer": "#E13342",
        "security-analyst": "#E8403E",
        "senior-data-scientist": "#ED4F3E",
        "senior-researcher": "#F05E42",
        "senior-software-developer": "#F26C4A",
        "senior-ux-ui-specialist": "#F47A54",
        "senior-web-designer": "#F5875F",
        "shapeshifter": "#F5956B",
        "survivalist": "#F6A178",
        "swarm-strategist": "#F6AD86",
        "tcg-specialist": "#F6B995",
        "web-developer": "#F7C5A5"
      }
    },
    "rocket": {
      "domains": {
        "alchemy": "#0B0405",
        "bushcraft": "#160B13",
        "compliance": "#201322",
        "containerization": "#2A1B32",
        "data-serialization": "#322243",
        "defensive": "#382A54",
        "design": "#3D3266",
        "devops": "#403B78",
        "esoteric": "#404589",
        "gardening": "#3D5195",
        "general": "#395D9C",
        "git": "#36699F",
        "intellectual-property": "#3574A1",
        "jigsawr": "#347FA4",
        "mcp-integration": "#348CA7",
        "mlops": "#3497A9",
        "morphic": "#36A2AB",
        "observability": "#3AADAC",
        "project-management": "#42B9AD",
        "r-packages": "#4DC4AD",
        "reporting": "#60CEAC",
        "review": "#7DD6AF",
        "swarm": "#9ADDB6",
        "tcg": "#B4E4C3",
        "web-dev": "#CAEDD4",
        "workflow-visualization": "#DEF5E5"
      },
      "agents": {
        "alchemist": "#26172A",
        "auditor": "#2C1C36",
        "code-reviewer": "#322243",
        "designer": "#37284F",
        "devops-engineer": "#3B2E5C",
        "gardener": "#3E346A",
        "gxp-validator": "#403B78",
        "ip-analyst": "#414184",
        "jigsawr-developer": "#3F4A8F",
        "martial-artist": "#3D5297",
        "mlops-engineer": "#3A5C9B",
        "mystic": "#37659E",
        "polymath": "#366DA0",
        "project-manager": "#3576A2",
        "putior-integrator": "#357EA4",
        "quarto-developer": "#3487A6",
        "r-developer": "#348FA7",
        "security-analyst": "#3498A9",
        "senior-data-scientist": "#35A1AB",
        "senior-researcher": "#38A9AC",
        "senior-software-developer": "#3CB2AD",
        "senior-ux-ui-specialist": "#42B9AD",
        "senior-web-designer": "#4AC2AD",
        "shapeshifter": "#56CAAD",
        "survivalist": "#68D1AD",
        "swarm-strategist": "#7DD6AF",
        "tcg-specialist": "#94DCB5",
        "web-developer": "#A8E1BC"
      }
    },
    "turbo": {
      "domains": {
        "alchemy": "#30123B",
        "bushcraft": "#3B3081",
        "compliance": "#424CB7",
        "containerization": "#4668DF",
        "data-serialization": "#4682F8",
        "defensive": "#3E9BFE",
        "design": "#2EB5F2",
        "devops": "#1DCCD9",
        "esoteric": "#18DFBE",
        "gardening": "#27EEA5",
        "general": "#46F884",
        "git": "#6EFE61",
        "intellectual-property": "#94FF46",
        "jigsawr": "#B0F936",
        "mcp-integration": "#CAED34",
        "mlops": "#E1DD37",
        "morphic": "#F2C93A",
        "observability": "#FCB236",
        "project-management": "#FE972B",
        "r-packages": "#F9791E",
        "reporting": "#F05B12",
        "review": "#E2430A",
        "swarm": "#CF2E05",
        "tcg": "#B81D02",
        "web-dev": "#9C0F01",
        "workflow-visualization": "#7A0403"
      },
      "agents": {
        "alchemist": "#455BCD",
        "auditor": "#476EE6",
        "code-reviewer": "#4681F7",
        "designer": "#4294FF",
        "devops-engineer": "#37A7FA",
        "gardener": "#29BAED",
        "gxp-validator": "#1ECBDA",
        "ip-analyst": "#18DAC7",
        "jigsawr-developer": "#1CE6B4",
        "martial-artist": "#2BEFA0",
        "mlops-engineer": "#43F787",
        "mystic": "#5FFC6D",
        "polymath": "#7EFF55",
        "project-manager": "#98FE43",
        "putior-integrator": "#ADFB38",
        "quarto-developer": "#C1F334",
        "r-developer": "#D3E835",
        "security-analyst": "#E3DB38",
        "senior-data-scientist": "#F0CC3A",
        "senior-researcher": "#F9BC39",
        "senior-software-developer": "#FEAA33",
        "senior-ux-ui-specialist": "#FE952B",
        "senior-web-designer": "#FB7F21",
        "shapeshifter": "#F56818",
        "survivalist": "#EC530F",
        "swarm-strategist": "#E2420A",
        "tcg-specialist": "#D43305",
        "web-developer": "#C42503"
      }
    }
  }
}
